CHANGELOG
LICENSE
MANIFEST.in
README
setup.cfg
setup.py
scripts/stellaris
stellaris/__init__.py
stellaris/dbmodels.py
stellaris/env.py
stellaris/exceptions.py
stellaris/graph.py
stellaris/indexmanager.py
stellaris/message.py
stellaris/scheduler.py
stellaris/security.py
stellaris/serialize.py
stellaris/storemanager.py
stellaris/utils.py
stellaris/worker.py
stellaris.egg-info/PKG-INFO
stellaris.egg-info/SOURCES.txt
stellaris.egg-info/dependency_links.txt
stellaris.egg-info/not-zip-safe
stellaris.egg-info/requires.txt
stellaris.egg-info/top_level.txt
stellaris/data/__init__.py
stellaris/data/etc/stellaris.cfg
stellaris/data/etc/stellaris.wsgi
stellaris/data/etc/virtuoso.ini_tmpl
stellaris/data/static/css/style.css
stellaris/data/static/css/tablesorter_blue.css
stellaris/data/static/css/tablesorter_green.css
stellaris/data/static/html/graphs.html
stellaris/data/static/html/query.html
stellaris/data/static/img/asc.gif
stellaris/data/static/img/asc.png
stellaris/data/static/img/bg.gif
stellaris/data/static/img/bg.png
stellaris/data/static/img/busy.gif
stellaris/data/static/img/desc.gif
stellaris/data/static/img/desc.png
stellaris/data/static/js/graphs.js
stellaris/data/static/js/jquery.form.js
stellaris/data/static/js/jquery.js
stellaris/data/static/js/jquery.stellaris.js
stellaris/data/static/js/jquery.tablesorter.js
stellaris/data/static/js/query.js
stellaris/index/__init__.py
stellaris/index/backend.py
stellaris/index/concurrent.py
stellaris/index/exceptions.py
stellaris/index/native.py
stellaris/index/sesame.py
stellaris/index/virtuoso.py
stellaris/service/__init__.py
stellaris/service/collections.py
stellaris/service/graphs.py
stellaris/service/groups.py
stellaris/service/query.py
stellaris/service/security.py
stellaris/service/serve.py
stellaris/service/static.py
stellaris/service/system.py
stellaris/service/tasks.py
stellaris/store/__init__.py
stellaris/store/backend.py
stellaris/store/cache.py
stellaris/store/exceptions.py
stellaris/store/federation.py
stellaris/store/frontend.py
stellaris/store/lifetime.py
stellaris/store/rdbms.py
stellaris/store/secure.py
stellaris/store/stage.py
stellaris/store/store.py
stellaris/store/version.py
tests/__init__.py
