Metadata-Version: 1.0
Name: stellaris
Version: 0.3.2
Summary: Stellaris is a metadata management service.
Home-page: http://stellaris.zib.de/
Author: Mikael Hoegqvist
Author-email: hoegqvist@zib.de
License: Apache License version 2.0
Platform: any
Classifier: Programming Language :: Python
Classifier: Development Status :: 4 - Beta
Classifier: Operating System :: POSIX
Classifier: Topic :: Database :: Database Engines/Servers
Classifier: Topic :: Internet :: WWW/HTTP :: WSGI :: Application
